mathex/__init__.py
mathex/config.py
mathex/enums.py
mathex/error.py
mathex/evaluate.py
mathex/token.py
mathex-0.2.0.dist-info/METADATA
mathex-0.2.0.dist-info/WHEEL
mathex-0.2.0.dist-info/licenses/LICENSE
mathex-0.2.0.dist-info/RECORD
