Metadata-Version: 2.1
Name: mathex
Version: 0.2.0
Summary: Package for Python that evaluates math expressions from strings
Project-URL: Homepage, https://github.com/capsey/mathex-py
Project-URL: Bug Tracker, https://github.com/capsey/mathex-py/issues
Author-email: Caps Lock <lockedcapsey@gmail.com>
License-File: LICENSE
Classifier: License :: OSI Approved :: MIT License
Classifier: Operating System :: OS Independent
Classifier: Programming Language :: Python :: 3
Requires-Python: >=3.7
